{"data": {"event": {"id": "8a93ee44-0af5-456f-beef-1cae7debc467", "picture": "https://services.medicalcongress.online/congress/medias/2025/JFR2025/538/video/thumbs/poster.jpg", "sessionType": "A vous la sonde", "sessionTypeColor": "#000000", "voting": null, "title": "Main :\u00a0ligament ulnaire de la MCP du pouce", "start": "2025-10-03T10:15+02:00", "end": "2025-10-03T10:45+02:00", "objectives": [], "onAir": null, "vod": null, "broadcasts": {"items": []}, "room": {"id": "7bf51aaa-7125-478a-9a6d-f95dfdb87bbf", "name": "VUS", "type": "ROOM"}, "schedule": {"items": [{"id": "46a42639-1c76-430f-8741-d9d30005e184", "title": "Main :  ligament ulnaire de la MCP du pouce", "start": "2025-10-03T10:15+02:00", "end": "2025-10-03T10:45+02:00", "element": {"abstract": null}, "speakers": {"items": [{"id": "25bcd317-8fbc-4f34-9abd-72c4601678ed", "lastName": "Ferary", "firstName": "Elodie", "roles": [{"name": "speaker"}], "photo": {"url": "https://services.y-congress.com/congress/wspreview/getphoto.aspx?idPhoto=202245&t=1"}, "country": {"name": "France"}, "city": {"name": "Hyeres"}}]}, "vod": null}]}, "roles": [], "speakers": {"items": [{"id": "25bcd317-8fbc-4f34-9abd-72c4601678ed", "firstName": "Elodie", "lastName": "Ferary", "photo": {"url": "https://services.y-congress.com/congress/wspreview/getphoto.aspx?idPhoto=202245&t=1"}, "country": {"name": "France"}, "city": {"name": "Hyeres"}}]}, "chairs": {"items": []}, "topics": [], "tracks": [], "organizers": [{"id": "f23af489-cfec-4c1f-a584-478d481ba587", "name": "SIMS", "logo": null}], "programmeOwners": [{"title": "JFR 2025", "id": "57f4784e-6ab3-4189-9e85-b0ddf3d47b2a"}]}}}