{"data": {"event": {"id": "4beb435c-d2ff-425f-9bcc-18e7c4dc0667", "picture": "https://services.medicalcongress.online/congress/medias/2025/JFR2025/797/video/thumbs/poster.jpg", "sessionType": "S\u00e9ance p\u00e9dagogique", "sessionTypeColor": "#44bdfa", "voting": null, "title": "Your JFR - What's new about cardiomyopathy in 2025", "start": "2025-10-04T10:30+02:00", "end": "2025-10-04T12:00+02:00", "objectives": ["<div><span style=\"font-size: 14px;\">Identify the clinical, electrocardiographic, and morphological features of hypertrophic cardiomyopathy, arrhythmogenic cardiomyopathy, non-dilated left ventricular cardiomyopathy, and dilated cardiomyopathy.</span></div>", "<div>&nbsp;</div>", "<div><span style=\"font-size: 14px;\">Differentiate these types of cardiomyopathies in terms of etiology, diagnostic approach (including imaging, genetics, and biomarkers), and prognosis.</span></div>", "<div>&nbsp;</div>", "<div><span style=\"font-size: 14px;\">Discuss the therapeutic implications specific to each type of cardiomyopathy, including indications for medical treatment, ablation, implantable cardioverter-defibrillator (ICD), or heart transplantation.</span></div>"], "onAir": null, "vod": {"checkPermissions": ["media:view"], "media": null}, "broadcasts": {"items": []}, "room": {"id": "3f7f4794-c9d4-48a9-8b06-936079788503", "name": "243", "type": "ROOM"}, "schedule": {"items": [{"id": "7498dfcd-dff2-4c8c-8746-7b186951059f", "title": "Hypertrophic cardiomyopathy", "start": "2025-10-04T10:30+02:00", "end": "2025-10-04T10:52+02:00", "element": {"abstract": null}, "speakers": {"items": [{"id": "a2f5bbe7-22c0-43b3-a1db-c9955841dcf4", "lastName": "Hanneman", "firstName": "Kate", "roles": [{"name": "speaker"}], "photo": {"url": "https://services.y-congress.com/congress/wspreview/getphoto.aspx?idPhoto=202352&t=1"}, "country": {"name": "Canada"}, "city": {"name": "Toronto"}}]}, "vod": {"checkPermissions": ["media:view"], "media": {"id": "cfca7958-880d-473a-ba38-1615836cc78d", "type": "VIDEO", "thumbnail": "https://services.medicalcongress.online/congress/medias/2025/JFR2025/797/video/thumbs/poster.jpg", "element": {"sources": [{"uri": "https://services.medicalcongress.online/congress/medias/2025/JFR2025/797/video/s_1080p_4000kb.mp4?verify=1760028889-EKaNy05viIYFnVdjA%2FgAzTyeLiYGM6sSne2B8e%2F77zk%3D"}, {"uri": "https://services.medicalcongress.online/congress/medias/2025/JFR2025/797/video/s_480p_800kb.mp4?verify=1760028889-ai7PEUl51kxskacx0YpkcytrzVjqVpqce0QgArnXlGo%3D"}]}}}}, {"id": "561aad85-f178-47c4-87b3-afc43ad58f90", "title": "Arrythmogenic cardiomyopathy", "start": "2025-10-04T10:52+02:00", "end": "2025-10-04T11:14+02:00", "element": {"abstract": null}, "speakers": {"items": [{"id": "fbf39f1f-59ed-4d2c-b95e-9b542f3d109d", "lastName": "Goerne", "firstName": "Harold", "roles": [{"name": "speaker"}], "photo": {"url": "https://services.y-congress.com/congress/wspreview/getphoto.aspx?idPhoto=202348&t=1"}, "country": {"name": "Mexique"}, "city": {"name": "Guadalajara"}}]}, "vod": {"checkPermissions": ["media:view"], "media": {"id": "8a049427-d8e0-4043-814d-19f69385467f", "type": "VIDEO", "thumbnail": "https://services.medicalcongress.online/congress/medias/2025/JFR2025/798/video/thumbs/poster.jpg", "element": {"sources": [{"uri": "https://services.medicalcongress.online/congress/medias/2025/JFR2025/798/video/s_1080p_4000kb.mp4?verify=1760028889-FsJ3jDRCA8gFPz8vqImMRQGhkwt8hPAbZSwL2fOQAF0%3D"}, {"uri": "https://services.medicalcongress.online/congress/medias/2025/JFR2025/798/video/s_480p_800kb.mp4?verify=1760028889-d%2B4lMZREV8pWvpCnYoeBpOnEI0ocY9wCEhQzyriP9ho%3D"}]}}}}, {"id": "28c74f12-3405-4ddc-8fce-c59433b1eb31", "title": "Non dilated LV cardiomyopath", "start": "2025-10-04T11:14+02:00", "end": "2025-10-04T11:36+02:00", "element": {"abstract": null}, "speakers": {"items": [{"id": "3d8d92f5-7749-4824-8ccf-6107ba60c2cb", "lastName": "Kurata", "firstName": "Akira", "roles": [{"name": "speaker"}], "photo": null, "country": {"name": "Japon"}, "city": {"name": "Matsuyama"}}]}, "vod": {"checkPermissions": ["media:view"], "media": {"id": "7d39ad75-2cb8-4fb5-bb3f-7e57fbbe2a25", "type": "VIDEO", "thumbnail": "https://services.medicalcongress.online/congress/medias/2025/JFR2025/800/video/thumbs/poster.jpg", "element": {"sources": [{"uri": "https://services.medicalcongress.online/congress/medias/2025/JFR2025/800/video/s_1080p_4000kb.mp4?verify=1760028889-kAqDGCLCOYa6p%2BUjQAZJxDzNZ6L3cZBdB0GRqV%2FbdkI%3D"}, {"uri": "https://services.medicalcongress.online/congress/medias/2025/JFR2025/800/video/s_480p_800kb.mp4?verify=1760028889-EoGC5D7WZe%2Bn00%2BvYY4et43OsEqaiPTiH5nKSmi5pCg%3D"}]}}}}, {"id": "8d257b0e-16c2-47fa-bc2a-739559a71255", "title": "Dilated cardiomyopathy", "start": "2025-10-04T11:36+02:00", "end": "2025-10-04T11:58+02:00", "element": {"abstract": null}, "speakers": {"items": [{"id": "0ee742ac-09db-4b22-9caa-7cc23383f22f", "lastName": "Bartoli", "firstName": "Axel", "roles": [{"name": "speaker"}], "photo": {"url": "https://services.y-congress.com/congress/wspreview/getphoto.aspx?idPhoto=202052&t=1"}, "country": {"name": "France"}, "city": {"name": "Marseille"}}]}, "vod": {"checkPermissions": ["media:view"], "media": {"id": "2d4b1856-cf10-4730-86f7-f0901c6e2cc3", "type": "VIDEO", "thumbnail": "https://services.medicalcongress.online/congress/medias/2025/JFR2025/799/video/thumbs/poster.jpg", "element": {"sources": [{"uri": "https://services.medicalcongress.online/congress/medias/2025/JFR2025/799/video/s_1080p_4000kb.mp4?verify=1760028889-O0M6Fza%2BBhC3oZICtO363lfzLKBXGd8vzmHxOyNcTIM%3D"}, {"uri": "https://services.medicalcongress.online/congress/medias/2025/JFR2025/799/video/s_480p_800kb.mp4?verify=1760028889-1h8auTGInPtQUEF%2BcJHZuPvjNxIkfbRrGl3856KmMzI%3D"}]}}}}]}, "roles": [{"name": "mod\u00e9rateur", "assignees": {"items": [{"id": "0b0a0bd5-0602-44ef-9662-851ad386fca9", "firstName": "Alexis", "lastName": "Jacquier", "photo": {"url": "https://services.y-congress.com/congress/wspreview/getphoto.aspx?idPhoto=202615&t=1"}, "country": {"name": "France"}, "city": {"name": "Marseille"}}, {"id": "0ee742ac-09db-4b22-9caa-7cc23383f22f", "firstName": "Axel", "lastName": "Bartoli", "photo": {"url": "https://services.y-congress.com/congress/wspreview/getphoto.aspx?idPhoto=202052&t=1"}, "country": {"name": "France"}, "city": {"name": "Marseille"}}]}}], "speakers": {"items": [{"id": "a2f5bbe7-22c0-43b3-a1db-c9955841dcf4", "firstName": "Kate", "lastName": "Hanneman", "photo": {"url": "https://services.y-congress.com/congress/wspreview/getphoto.aspx?idPhoto=202352&t=1"}, "country": {"name": "Canada"}, "city": {"name": "Toronto"}}, {"id": "0ee742ac-09db-4b22-9caa-7cc23383f22f", "firstName": "Axel", "lastName": "Bartoli", "photo": {"url": "https://services.y-congress.com/congress/wspreview/getphoto.aspx?idPhoto=202052&t=1"}, "country": {"name": "France"}, "city": {"name": "Marseille"}}, {"id": "3d8d92f5-7749-4824-8ccf-6107ba60c2cb", "firstName": "Akira", "lastName": "Kurata", "photo": null, "country": {"name": "Japon"}, "city": {"name": "Matsuyama"}}, {"id": "fbf39f1f-59ed-4d2c-b95e-9b542f3d109d", "firstName": "Harold", "lastName": "Goerne", "photo": {"url": "https://services.y-congress.com/congress/wspreview/getphoto.aspx?idPhoto=202348&t=1"}, "country": {"name": "Mexique"}, "city": {"name": "Guadalajara"}}]}, "chairs": {"items": []}, "topics": [{"_id": "c7c29343-d668-49ce-ae99-e0198b9ac254", "value": "Cardiovasculaire"}], "tracks": [{"color": "", "id": "d8cfd75f-6879-4314-b2cf-e3978a8173ba", "value": "Parcours international", "label": "Parcours international"}], "organizers": [{"id": "747359ad-6f2d-4627-9d6d-9aa8cc966a00", "name": "SFICV", "logo": null}], "programmeOwners": [{"title": "JFR 2025", "id": "57f4784e-6ab3-4189-9e85-b0ddf3d47b2a"}, {"title": "International", "id": "97a56815-7ad3-440e-9284-4d471c3f0d80"}]}}}